phy_django/__init__.py
phy_django/admin.py
phy_django/apps.py
phy_django/forms.py
phy_django/models.py
phy_django/resources.py
phy_django/runs.py
phy_django/serializers.py
phy_django/tests.py
phy_django/views.py
phy_django/viewsets.py
phy_django/migrations/0001_initial.py
phy_django/migrations/0002_configuration.py
phy_django/migrations/0003_configuration_user.py
phy_django/migrations/0004_alter_configuration_value.py
phy_django/migrations/__init__.py
phy_django/templates/admin/change_form.html
phy_django/templates/phy_django/403.html
phy_django/templates/phy_django/base.html
phy_django/templates/phy_django/form.html
phy_django/templates/phy_django/nav.html
phy_django/templates/phy_django/page.html
phy_django-0.0.18.dist-info/LICENSE
phy_django-0.0.18.dist-info/METADATA
phy_django-0.0.18.dist-info/WHEEL
phy_django-0.0.18.dist-info/top_level.txt
phy_django-0.0.18.dist-info/RECORD
