Metadata-Version: 2.1
Name: phy-django
Version: 0.0.18
Summary: My personal django enhancement library.
Home-page: https://github.com/panhaoyu/phy_django.git
Author: Haoyu Pan
Author-email: panhaoyu.china@outlook.com
License: UNKNOWN
Platform: UNKNOWN
Classifier: Programming Language :: Python :: 3
Classifier: License :: OSI Approved :: MIT License
Classifier: Operating System :: OS Independent
Requires-Python: >=3.7
License-File: LICENSE
Requires-Dist: django
Requires-Dist: django-rest-framework
Requires-Dist: django-q
Requires-Dist: django-dump-load-utf8
Requires-Dist: django-admin-object-button
Requires-Dist: django-silk
Requires-Dist: django-money
Requires-Dist: django-registration
Requires-Dist: django-crispy-forms
Requires-Dist: django-guardian
Requires-Dist: django-extensions
Requires-Dist: django-import-export
Requires-Dist: django-nested-admin
Requires-Dist: django-json-widget
